{
  "schemaVersion": 7,
  "stage": "8E",
  "revisedAtStage": "8Q",
  "recordedAt": "2026-07-21",
  "status": "custom_domains_https_and_host_isolation_verified_waiting_private_values",
  "recommendedBootstrapWorkflow": "stage8h-edgeone-production-bootstrap",
  "bootstrapRequiresOwnerDomain": false,
  "deploymentBootstrapPathDeprecated": true,
  "domain": {
    "registrableDomain": "xiaxue.site",
    "publicHostname": "app.xiaxue.site",
    "administratorHostname": "admin.xiaxue.site",
    "publicOrigin": "https://app.xiaxue.site",
    "administratorOrigin": "https://admin.xiaxue.site",
    "ownershipConfirmed": true,
    "realNameConfirmed": true,
    "registrationDate": "2026-07-21",
    "expirationDate": "2027-07-21",
    "autoRenewEnabled": true,
    "dnsProvider": "DNSPod",
    "dnsControlConfirmed": true,
    "customDomainsAddedToSameProject": true,
    "customDomainProvisioning": {
      "app.xiaxue.site": {
        "status": "active",
        "cnameVisible": true,
        "cnameTarget": "app.xiaxue.site.pages.dnsoe6.com.",
        "httpsConfigured": true,
        "realBrowserAccessVerified": true
      },
      "admin.xiaxue.site": {
        "status": "active",
        "cnameVisible": true,
        "cnameTarget": "admin.xiaxue.site.pages.dnsoe4.com.",
        "httpsConfigured": true,
        "realBrowserAccessVerified": true
      }
    },
    "dnsConfigured": true,
    "httpsVerified": true,
    "hostIsolationRealBrowserVerified": true
  },
  "deployment": {
    "initialAccelerationRegion": "global_excluding_chinese_mainland",
    "accelerationRegionVerified": true,
    "icpFilingRequiredForInitialRegion": false,
    "icpFilingDeferred": true,
    "mainlandAccelerationEnabled": false,
    "eligibleMainlandCloudResourcePurchased": false,
    "cloudServerPurchaseRequiredNow": false,
    "futureMainlandAccelerationRequiresIcpFiling": true
  },
  "architecture": {
    "topology": "single_edgeone_project_two_custom_domains",
    "edgeOneProjectCount": 1,
    "singleProjectHostIsolationImplemented": true,
    "singleProjectHostIsolationRealBrowserVerified": true,
    "currentProjectScopedBlobResolved": true,
    "accountApiTokenInLongRunningRuntimeAllowed": false,
    "administratorSeparateProjectRequired": false,
    "administratorSeparateProjectCreationForbidden": true,
    "realBootstrapBlockedByArchitecture": false,
    "realBootstrapAuthorized": false,
    "resolution": "single_project_two_domain_host_isolation"
  },
  "privateValuesGenerated": false,
  "environmentVariablesWritten": false,
  "stablePromotionAuthorized": false,
  "stablePromotionPerformed": false,
  "productionActivationPerformed": false
}
